{"worldName": "custom", "options": {"imageURL": "textures/maps/grid.png", "groundType": "box", "length": 360, "width": 360, "uScale": 8, "vScale": 8, "imageScale": 5.3, "timer": "up", "timerDuration": 0, "timerEnd": "continue", "wall": true, "wallHeight": 10, "wallThickness": 4.5, "wallColor": "#1A1A1A", "groundFriction": 1, "wallFriction": 0.1, "groundRestitution": 0, "wallRestitution": 0.1, "restartAnimationOnRun": false, "objects": [{"type": "box", "position": [-157.5, -135.0, 5], "rotationMode": "degrees", "rotation": [0, 0, 0], "animationMode": "none", "animationKeys": [], "size": [45.0, 1, 10], "modelURL": "", "modelScale": 10, "modelAnimation": "None", "color": "#80E680", "imageType": "repeat", "imageURL": "", "uScale": 1, "vScale": 1, "physicsOptions": "fixed", "magnetic": false, "laserDetection": "null", "ultrasonicDetection": "null", "receiveShadows": false, "castShadows": false, "isPickable": true}, {"type": "box", "position": [-157.5, 45.0, 5], "rotationMode": "degrees", "rotation": [0, 0, 0], "animationMode": "none", "animationKeys": [], "size": [45.0, 1, 10], "modelURL": "", "modelScale": 10, "modelAnimation": "None", "color": "#80E680", "imageType": "repeat", "imageURL": "", "uScale": 1, "vScale": 1, "physicsOptions": "fixed", "magnetic": false, "laserDetection": "null", "ultrasonicDetection": "null", "receiveShadows": false, "castShadows": false, "isPickable": true}, {"type": "box", "position": [-112.5, -90.0, 5], "rotationMode": "degrees", "rotation": [0, 0, 0], "animationMode": "none", "animationKeys": [], "size": [45.0, 1, 10], "modelURL": "", "modelScale": 10, "modelAnimation": "None", "color": "#80E680", "imageType": "repeat", "imageURL": "", "uScale": 1, "vScale": 1, "physicsOptions": "fixed", "magnetic": false, "laserDetection": "null", "ultrasonicDetection": "null", "receiveShadows": false, "castShadows": false, "isPickable": true}, {"type": "box", "position": [-112.5, 0.0, 5], "rotationMode": "degrees", "rotation": [0, 0, 0], "animationMode": "none", "animationKeys": [], "size": [45.0, 1, 10], "modelURL": "", "modelScale": 10, "modelAnimation": "None", "color": "#80E680", "imageType": "repeat", "imageURL": "", "uScale": 1, "vScale": 1, "physicsOptions": "fixed", "magnetic": false, "laserDetection": "null", "ultrasonicDetection": "null", "receiveShadows": false, "castShadows": false, "isPickable": true}, {"type": "box", "position": [-90.0, 90.0, 5], "rotationMode": "degrees", "rotation": [0, 0, 0], "animationMode": "none", "animationKeys": [], "size": [90.0, 1, 10], "modelURL": "", "modelScale": 10, "modelAnimation": "None", "color": "#80E680", "imageType": "repeat", "imageURL": "", "uScale": 1, "vScale": 1, "physicsOptions": "fixed", "magnetic": false, "laserDetection": "null", "ultrasonicDetection": "null", "receiveShadows": false, "castShadows": false, "isPickable": true}, {"type": "box", "position": [-90.0, 135.0, 5], "rotationMode": "degrees", "rotation": [0, 0, 0], "animationMode": "none", "animationKeys": [], "size": [90.0, 1, 10], "modelURL": "", "modelScale": 10, "modelAnimation": "None", "color": "#80E680", "imageType": "repeat", "imageURL": "", "uScale": 1, "vScale": 1, "physicsOptions": "fixed", "magnetic": false, "laserDetection": "null", "ultrasonicDetection": "null", "receiveShadows": false, "castShadows": false, "isPickable": true}, {"type": "box", "position": [-22.5, -45.0, 5], "rotationMode": "degrees", "rotation": [0, 0, 0], "animationMode": "none", "animationKeys": [], "size": [45.0, 1, 10], "modelURL": "", "modelScale": 10, "modelAnimation": "None", "color": "#80E680", "imageType": "repeat", "imageURL": "", "uScale": 1, "vScale": 1, "physicsOptions": "fixed", "magnetic": false, "laserDetection": "null", "ultrasonicDetection": "null", "receiveShadows": false, "castShadows": false, "isPickable": true}, {"type": "box", "position": [-22.5, 45.0, 5], "rotationMode": "degrees", "rotation": [0, 0, 0], "animationMode": "none", "animationKeys": [], "size": [45.0, 1, 10], "modelURL": "", "modelScale": 10, "modelAnimation": "None", "color": "#80E680", "imageType": "repeat", "imageURL": "", "uScale": 1, "vScale": 1, "physicsOptions": "fixed", "magnetic": false, "laserDetection": "null", "ultrasonicDetection": "null", "receiveShadows": false, "castShadows": false, "isPickable": true}, {"type": "box", "position": [22.5, -90.0, 5], "rotationMode": "degrees", "rotation": [0, 0, 0], "animationMode": "none", "animationKeys": [], "size": [45.0, 1, 10], "modelURL": "", "modelScale": 10, "modelAnimation": "None", "color": "#80E680", "imageType": "repeat", "imageURL": "", "uScale": 1, "vScale": 1, "physicsOptions": "fixed", "magnetic": false, "laserDetection": "null", "ultrasonicDetection": "null", "receiveShadows": false, "castShadows": false, "isPickable": true}, {"type": "box", "position": [22.5, 0.0, 5], "rotationMode": "degrees", "rotation": [0, 0, 0], "animationMode": "none", "animationKeys": [], "size": [45.0, 1, 10], "modelURL": "", "modelScale": 10, "modelAnimation": "None", "color": "#80E680", "imageType": "repeat", "imageURL": "", "uScale": 1, "vScale": 1, "physicsOptions": "fixed", "magnetic": false, "laserDetection": "null", "ultrasonicDetection": "null", "receiveShadows": false, "castShadows": false, "isPickable": true}, {"type": "box", "position": [22.5, 90.0, 5], "rotationMode": "degrees", "rotation": [0, 0, 0], "animationMode": "none", "animationKeys": [], "size": [45.0, 1, 10], "modelURL": "", "modelScale": 10, "modelAnimation": "None", "color": "#80E680", "imageType": "repeat", "imageURL": "", "uScale": 1, "vScale": 1, "physicsOptions": "fixed", "magnetic": false, "laserDetection": "null", "ultrasonicDetection": "null", "receiveShadows": false, "castShadows": false, "isPickable": true}, {"type": "box", "position": [45.0, 135.0, 5], "rotationMode": "degrees", "rotation": [0, 0, 0], "animationMode": "none", "animationKeys": [], "size": [90.0, 1, 10], "modelURL": "", "modelScale": 10, "modelAnimation": "None", "color": "#80E680", "imageType": "repeat", "imageURL": "", "uScale": 1, "vScale": 1, "physicsOptions": "fixed", "magnetic": false, "laserDetection": "null", "ultrasonicDetection": "null", "receiveShadows": false, "castShadows": false, "isPickable": true}, {"type": "box", "position": [90.0, 45.0, 5], "rotationMode": "degrees", "rotation": [0, 0, 0], "animationMode": "none", "animationKeys": [], "size": [90.0, 1, 10], "modelURL": "", "modelScale": 10, "modelAnimation": "None", "color": "#80E680", "imageType": "repeat", "imageURL": "", "uScale": 1, "vScale": 1, "physicsOptions": "fixed", "magnetic": false, "laserDetection": "null", "ultrasonicDetection": "null", "receiveShadows": false, "castShadows": false, "isPickable": true}, {"type": "box", "position": [112.5, -135.0, 5], "rotationMode": "degrees", "rotation": [0, 0, 0], "animationMode": "none", "animationKeys": [], "size": [45.0, 1, 10], "modelURL": "", "modelScale": 10, "modelAnimation": "None", "color": "#80E680", "imageType": "repeat", "imageURL": "", "uScale": 1, "vScale": 1, "physicsOptions": "fixed", "magnetic": false, "laserDetection": "null", "ultrasonicDetection": "null", "receiveShadows": false, "castShadows": false, "isPickable": true}, {"type": "box", "position": [112.5, -90.0, 5], "rotationMode": "degrees", "rotation": [0, 0, 0], "animationMode": "none", "animationKeys": [], "size": [45.0, 1, 10], "modelURL": "", "modelScale": 10, "modelAnimation": "None", "color": "#80E680", "imageType": "repeat", "imageURL": "", "uScale": 1, "vScale": 1, "physicsOptions": "fixed", "magnetic": false, "laserDetection": "null", "ultrasonicDetection": "null", "receiveShadows": false, "castShadows": false, "isPickable": true}, {"type": "box", "position": [112.5, 0.0, 5], "rotationMode": "degrees", "rotation": [0, 0, 0], "animationMode": "none", "animationKeys": [], "size": [45.0, 1, 10], "modelURL": "", "modelScale": 10, "modelAnimation": "None", "color": "#80E680", "imageType": "repeat", "imageURL": "", "uScale": 1, "vScale": 1, "physicsOptions": "fixed", "magnetic": false, "laserDetection": "null", "ultrasonicDetection": "null", "receiveShadows": false, "castShadows": false, "isPickable": true}, {"type": "box", "position": [112.5, 90.0, 5], "rotationMode": "degrees", "rotation": [0, 0, 0], "animationMode": "none", "animationKeys": [], "size": [45.0, 1, 10], "modelURL": "", "modelScale": 10, "modelAnimation": "None", "color": "#80E680", "imageType": "repeat", "imageURL": "", "uScale": 1, "vScale": 1, "physicsOptions": "fixed", "magnetic": false, "laserDetection": "null", "ultrasonicDetection": "null", "receiveShadows": false, "castShadows": false, "isPickable": true}, {"type": "box", "position": [157.5, -45.0, 5], "rotationMode": "degrees", "rotation": [0, 0, 0], "animationMode": "none", "animationKeys": [], "size": [45.0, 1, 10], "modelURL": "", "modelScale": 10, "modelAnimation": "None", "color": "#80E680", "imageType": "repeat", "imageURL": "", "uScale": 1, "vScale": 1, "physicsOptions": "fixed", "magnetic": false, "laserDetection": "null", "ultrasonicDetection": "null", "receiveShadows": false, "castShadows": false, "isPickable": true}, {"type": "box", "position": [-135.0, -45.0, 5], "rotationMode": "degrees", "rotation": [0, 0, 0], "animationMode": "none", "animationKeys": [], "size": [1, 90.0, 10], "modelURL": "", "modelScale": 10, "modelAnimation": "None", "color": "#80E680", "imageType": "repeat", "imageURL": "", "uScale": 1, "vScale": 1, "physicsOptions": "fixed", "magnetic": false, "laserDetection": "null", "ultrasonicDetection": "null", "receiveShadows": false, "castShadows": false, "isPickable": true}, {"type": "box", "position": [-135.0, 67.5, 5], "rotationMode": "degrees", "rotation": [0, 0, 0], "animationMode": "none", "animationKeys": [], "size": [1, 45.0, 10], "modelURL": "", "modelScale": 10, "modelAnimation": "None", "color": "#80E680", "imageType": "repeat", "imageURL": "", "uScale": 1, "vScale": 1, "physicsOptions": "fixed", "magnetic": false, "laserDetection": "null", "ultrasonicDetection": "null", "receiveShadows": false, "castShadows": false, "isPickable": true}, {"type": "box", "position": [-90.0, -135.0, 5], "rotationMode": "degrees", "rotation": [0, 0, 0], "animationMode": "none", "animationKeys": [], "size": [1, 90.0, 10], "modelURL": "", "modelScale": 10, "modelAnimation": "None", "color": "#80E680", "imageType": "repeat", "imageURL": "", "uScale": 1, "vScale": 1, "physicsOptions": "fixed", "magnetic": false, "laserDetection": "null", "ultrasonicDetection": "null", "receiveShadows": false, "castShadows": false, "isPickable": true}, {"type": "box", "position": [-90.0, 0.0, 5], "rotationMode": "degrees", "rotation": [0, 0, 0], "animationMode": "none", "animationKeys": [], "size": [1, 90.0, 10], "modelURL": "", "modelScale": 10, "modelAnimation": "None", "color": "#80E680", "imageType": "repeat", "imageURL": "", "uScale": 1, "vScale": 1, "physicsOptions": "fixed", "magnetic": false, "laserDetection": "null", "ultrasonicDetection": "null", "receiveShadows": false, "castShadows": false, "isPickable": true}, {"type": "box", "position": [-45.0, 0.0, 5], "rotationMode": "degrees", "rotation": [0, 0, 0], "animationMode": "none", "animationKeys": [], "size": [1, 270.0, 10], "modelURL": "", "modelScale": 10, "modelAnimation": "None", "color": "#80E680", "imageType": "repeat", "imageURL": "", "uScale": 1, "vScale": 1, "physicsOptions": "fixed", "magnetic": false, "laserDetection": "null", "ultrasonicDetection": "null", "receiveShadows": false, "castShadows": false, "isPickable": true}, {"type": "box", "position": [0.0, -135.0, 5], "rotationMode": "degrees", "rotation": [0, 0, 0], "animationMode": "none", "animationKeys": [], "size": [1, 90.0, 10], "modelURL": "", "modelScale": 10, "modelAnimation": "None", "color": "#80E680", "imageType": "repeat", "imageURL": "", "uScale": 1, "vScale": 1, "physicsOptions": "fixed", "magnetic": false, "laserDetection": "null", "ultrasonicDetection": "null", "receiveShadows": false, "castShadows": false, "isPickable": true}, {"type": "box", "position": [0.0, 112.5, 5], "rotationMode": "degrees", "rotation": [0, 0, 0], "animationMode": "none", "animationKeys": [], "size": [1, 45.0, 10], "modelURL": "", "modelScale": 10, "modelAnimation": "None", "color": "#80E680", "imageType": "repeat", "imageURL": "", "uScale": 1, "vScale": 1, "physicsOptions": "fixed", "magnetic": false, "laserDetection": "null", "ultrasonicDetection": "null", "receiveShadows": false, "castShadows": false, "isPickable": true}, {"type": "box", "position": [45.0, -157.5, 5], "rotationMode": "degrees", "rotation": [0, 0, 0], "animationMode": "none", "animationKeys": [], "size": [1, 45.0, 10], "modelURL": "", "modelScale": 10, "modelAnimation": "None", "color": "#80E680", "imageType": "repeat", "imageURL": "", "uScale": 1, "vScale": 1, "physicsOptions": "fixed", "magnetic": false, "laserDetection": "null", "ultrasonicDetection": "null", "receiveShadows": false, "castShadows": false, "isPickable": true}, {"type": "box", "position": [45.0, 0.0, 5], "rotationMode": "degrees", "rotation": [0, 0, 0], "animationMode": "none", "animationKeys": [], "size": [1, 180.0, 10], "modelURL": "", "modelScale": 10, "modelAnimation": "None", "color": "#80E680", "imageType": "repeat", "imageURL": "", "uScale": 1, "vScale": 1, "physicsOptions": "fixed", "magnetic": false, "laserDetection": "null", "ultrasonicDetection": "null", "receiveShadows": false, "castShadows": false, "isPickable": true}, {"type": "box", "position": [90.0, -45.0, 5], "rotationMode": "degrees", "rotation": [0, 0, 0], "animationMode": "none", "animationKeys": [], "size": [1, 90.0, 10], "modelURL": "", "modelScale": 10, "modelAnimation": "None", "color": "#80E680", "imageType": "repeat", "imageURL": "", "uScale": 1, "vScale": 1, "physicsOptions": "fixed", "magnetic": false, "laserDetection": "null", "ultrasonicDetection": "null", "receiveShadows": false, "castShadows": false, "isPickable": true}, {"type": "box", "position": [135.0, -112.5, 5], "rotationMode": "degrees", "rotation": [0, 0, 0], "animationMode": "none", "animationKeys": [], "size": [1, 45.0, 10], "modelURL": "", "modelScale": 10, "modelAnimation": "None", "color": "#80E680", "imageType": "repeat", "imageURL": "", "uScale": 1, "vScale": 1, "physicsOptions": "fixed", "magnetic": false, "laserDetection": "null", "ultrasonicDetection": "null", "receiveShadows": false, "castShadows": false, "isPickable": true}, {"type": "box", "position": [135.0, 22.5, 5], "rotationMode": "degrees", "rotation": [0, 0, 0], "animationMode": "none", "animationKeys": [], "size": [1, 45.0, 10], "modelURL": "", "modelScale": 10, "modelAnimation": "None", "color": "#80E680", "imageType": "repeat", "imageURL": "", "uScale": 1, "vScale": 1, "physicsOptions": "fixed", "magnetic": false, "laserDetection": "null", "ultrasonicDetection": "null", "receiveShadows": false, "castShadows": false, "isPickable": true}, {"type": "box", "position": [135.0, 135.0, 5], "rotationMode": "degrees", "rotation": [0, 0, 0], "animationMode": "none", "animationKeys": [], "size": [1, 90.0, 10], "modelURL": "", "modelScale": 10, "modelAnimation": "None", "color": "#80E680", "imageType": "repeat", "imageURL": "", "uScale": 1, "vScale": 1, "physicsOptions": "fixed", "magnetic": false, "laserDetection": "null", "ultrasonicDetection": "null", "receiveShadows": false, "castShadows": false, "isPickable": true}, {"type": "cylinder", "position": [-67.5, 112.5, 20], "rotationMode": "degrees", "rotation": [0, 0, 0], "animationMode": "none", "animationKeys": [], "size": [1, 7.0, 1], "modelURL": "", "modelScale": 10, "modelAnimation": "None", "color": "#ff0000", "imageType": "cylinder", "imageURL": "", "uScale": 1, "vScale": 1, "physicsOptions": "moveable", "magnetic": true, "laserDetection": "null", "ultrasonicDetection": "null", "receiveShadows": false, "castShadows": false, "isPickable": true}, {"type": "cylinder", "position": [22.5, 112.5, 20], "rotationMode": "degrees", "rotation": [0, 0, 0], "animationMode": "none", "animationKeys": [], "size": [1, 7.0, 1], "modelURL": "", "modelScale": 10, "modelAnimation": "None", "color": "#ff0000", "imageType": "cylinder", "imageURL": "", "uScale": 1, "vScale": 1, "physicsOptions": "moveable", "magnetic": true, "laserDetection": "null", "ultrasonicDetection": "null", "receiveShadows": false, "castShadows": false, "isPickable": true}, {"type": "cylinder", "position": [112.5, -112.5, 20], "rotationMode": "degrees", "rotation": [0, 0, 0], "animationMode": "none", "animationKeys": [], "size": [1, 7.0, 1], "modelURL": "", "modelScale": 10, "modelAnimation": "None", "color": "#ff0000", "imageType": "cylinder", "imageURL": "", "uScale": 1, "vScale": 1, "physicsOptions": "moveable", "magnetic": true, "laserDetection": "null", "ultrasonicDetection": "null", "receiveShadows": false, "castShadows": false, "isPickable": true}, {"type": "cylinder", "position": [-157.5, 67.5, 20], "rotationMode": "degrees", "rotation": [0, 0, 0], "animationMode": "none", "animationKeys": [], "size": [1, 7.0, 1], "modelURL": "", "modelScale": 10, "modelAnimation": "None", "color": "#0000ff", "imageType": "cylinder", "imageURL": "", "uScale": 1, "vScale": 1, "physicsOptions": "moveable", "magnetic": true, "laserDetection": "null", "ultrasonicDetection": "null", "receiveShadows": false, "castShadows": false, "isPickable": true}, {"type": "cylinder", "position": [112.5, 22.5, 20], "rotationMode": "degrees", "rotation": [0, 0, 0], "animationMode": "none", "animationKeys": [], "size": [1, 7.0, 1], "modelURL": "", "modelScale": 10, "modelAnimation": "None", "color": "#0000ff", "imageType": "cylinder", "imageURL": "", "uScale": 1, "vScale": 1, "physicsOptions": "moveable", "magnetic": true, "laserDetection": "null", "ultrasonicDetection": "null", "receiveShadows": false, "castShadows": false, "isPickable": true}, {"type": "cylinder", "position": [157.5, 157.5, 20], "rotationMode": "degrees", "rotation": [0, 0, 0], "animationMode": "none", "animationKeys": [], "size": [1, 7.0, 1], "modelURL": "", "modelScale": 10, "modelAnimation": "None", "color": "#0000ff", "imageType": "cylinder", "imageURL": "", "uScale": 1, "vScale": 1, "physicsOptions": "moveable", "magnetic": true, "laserDetection": "null", "ultrasonicDetection": "null", "receiveShadows": false, "castShadows": false, "isPickable": true}, {"type": "box", "position": [-157.5, 157.5, 0.1], "rotationMode": "degrees", "rotation": [0, 0, 0], "animationMode": "none", "animationKeys": [], "size": [45, 45, 0.1], "modelURL": "", "modelScale": 10, "modelAnimation": "None", "color": "#ff9494", "imageType": "repeat", "imageURL": "", "uScale": 1, "vScale": 1, "physicsOptions": "false", "magnetic": false, "laserDetection": "null", "ultrasonicDetection": "null", "receiveShadows": false, "castShadows": false, "isPickable": true}, {"type": "box", "position": [157.5, -157.5, 0.1], "rotationMode": "degrees", "rotation": [0, 0, 0], "animationMode": "none", "animationKeys": [], "size": [45, 45, 0.1], "modelURL": "", "modelScale": 10, "modelAnimation": "None", "color": "#9494ff", "imageType": "repeat", "imageURL": "", "uScale": 1, "vScale": 1, "physicsOptions": "false", "magnetic": false, "laserDetection": "null", "ultrasonicDetection": "null", "receiveShadows": false, "castShadows": false, "isPickable": true}], "startPos": "center", "startPosXYZStr": "", "startRotStr": "", "startPosXYZ": [-157.5, -157.5, 0], "startRot": "null", "arenaStartPosXYZ": "null", "arenaStartRot": "null"}}